pyrrencies/__init__.py
pyrrencies/main.py
pyrrencies-0.1.0.dist-info/LICENSE.md
pyrrencies-0.1.0.dist-info/METADATA
pyrrencies-0.1.0.dist-info/WHEEL
pyrrencies-0.1.0.dist-info/top_level.txt
pyrrencies-0.1.0.dist-info/RECORD
