Metadata-Version: 2.1
Name: pyrrencies
Version: 0.1.0
Summary: Comfortable work with currencies and currencies exchange rates
Home-page: https://github.com/de-jure/pyrrencies
Author: Yurii Plets
Author-email: de.jure.software@gmail.com
License: MIT
Keywords: currency currencies exchange rates
Platform: UNKNOWN
License-File: LICENSE.md
